{"cameraMode":{"drawMode":0,"name":"Shaded","section":"Shading Mode"},"sceneLighting":true,"audioPlay":false,"sceneViewState":{"m_AlwaysRefresh":false,"showFog":true,"showSkybox":true,"showFlares":true,"showImageEffects":true,"showParticleSystems":true,"showVisualEffectGraphs":true,"m_FxEnabled":true},"in2DMode":false,"pivot":{"x":-2977.162841796875,"y":-1076.4990234375,"z":1810.9326171875},"rotation":{"x":0.39391160011291506,"y":-0.246551975607872,"z":0.11054736375808716,"w":0.8785359263420105},"size":2840.102783203125,"orthographic":false}